pyregdict.py
pyregdict-0.2.dist-info/DESCRIPTION.rst
pyregdict-0.2.dist-info/METADATA
pyregdict-0.2.dist-info/RECORD
pyregdict-0.2.dist-info/WHEEL
pyregdict-0.2.dist-info/metadata.json
pyregdict-0.2.dist-info/top_level.txt
