Metadata-Version: 2.0
Name: pyregdict
Version: 0.2
Summary: Access to Windows Registry data as if a Unix file path.
Home-page: UNKNOWN
Author: Charles Aracil
Author-email: charles.aracil+pyregdict@gmail.com
License: MIT License
